laicrypto-0.2.0.dist-info/licenses/AUTHORS
laicrypto-0.2.0.dist-info/licenses/LICENSE
pqcrypto/__init__.py
pqcrypto/lai.py
laicrypto-0.2.0.dist-info/METADATA
laicrypto-0.2.0.dist-info/WHEEL
laicrypto-0.2.0.dist-info/top_level.txt
laicrypto-0.2.0.dist-info/RECORD
