Metadata-Version: 2.4
Name: laicrypto
Version: 0.2.0
Summary: Post-quantum Lemniscate-AGM Isogeny Encryption (LAI)
Author-email: GALIH RIDHO UTOMO <g4lihru@students.unnes.ac.id>
License: MIT
Project-URL: Homepage, https://github.com/galihru/pqcrypto
Project-URL: Repository, https://github.com/galihru/pqcrypto
Requires-Python: >=3.8
License-File: LICENSE
License-File: AUTHORS
Dynamic: license-file
